boardgamegeek/__init__.py
boardgamegeek/api.py
boardgamegeek/cache.py
boardgamegeek/exceptions.py
boardgamegeek/main.py
boardgamegeek/utils.py
boardgamegeek/version.py
boardgamegeek/loaders/__init__.py
boardgamegeek/loaders/collection.py
boardgamegeek/loaders/game.py
boardgamegeek/loaders/guild.py
boardgamegeek/loaders/hotitems.py
boardgamegeek/loaders/plays.py
boardgamegeek/objects/__init__.py
boardgamegeek/objects/collection.py
boardgamegeek/objects/games.py
boardgamegeek/objects/guild.py
boardgamegeek/objects/hotitems.py
boardgamegeek/objects/plays.py
boardgamegeek/objects/search.py
boardgamegeek/objects/things.py
boardgamegeek/objects/user.py
boardgamegeek2-1.0.1.dist-info/LICENSE
boardgamegeek2-1.0.1.dist-info/METADATA
boardgamegeek2-1.0.1.dist-info/WHEEL
boardgamegeek2-1.0.1.dist-info/entry_points.txt
boardgamegeek2-1.0.1.dist-info/top_level.txt
boardgamegeek2-1.0.1.dist-info/RECORD
